lisa_on_cuda/LISA.py
lisa_on_cuda/__init__.py
lisa_on_cuda/__version__.py
lisa_on_cuda/llava/__init__.py
lisa_on_cuda/llava/constants.py
lisa_on_cuda/llava/conversation.py
lisa_on_cuda/llava/mm_utils.py
lisa_on_cuda/llava/model/__init__.py
lisa_on_cuda/llava/model/apply_delta.py
lisa_on_cuda/llava/model/builder.py
lisa_on_cuda/llava/model/consolidate.py
lisa_on_cuda/llava/model/language_model/llava_llama.py
lisa_on_cuda/llava/model/language_model/llava_mpt.py
lisa_on_cuda/llava/model/language_model/mpt/adapt_tokenizer.py
lisa_on_cuda/llava/model/language_model/mpt/attention.py
lisa_on_cuda/llava/model/language_model/mpt/blocks.py
lisa_on_cuda/llava/model/language_model/mpt/configuration_mpt.py
lisa_on_cuda/llava/model/language_model/mpt/custom_embedding.py
lisa_on_cuda/llava/model/language_model/mpt/flash_attn_triton.py
lisa_on_cuda/llava/model/language_model/mpt/hf_prefixlm_converter.py
lisa_on_cuda/llava/model/language_model/mpt/meta_init_context.py
lisa_on_cuda/llava/model/language_model/mpt/modeling_mpt.py
lisa_on_cuda/llava/model/language_model/mpt/norm.py
lisa_on_cuda/llava/model/language_model/mpt/param_init_fns.py
lisa_on_cuda/llava/model/llava_arch.py
lisa_on_cuda/llava/model/make_delta.py
lisa_on_cuda/llava/model/multimodal_encoder/builder.py
lisa_on_cuda/llava/model/multimodal_encoder/clip_encoder.py
lisa_on_cuda/llava/model/utils.py
lisa_on_cuda/llava/train/llama_flash_attn_monkey_patch.py
lisa_on_cuda/llava/train/llava_trainer.py
lisa_on_cuda/llava/train/train.py
lisa_on_cuda/llava/train/train_mem.py
lisa_on_cuda/llava/utils.py
lisa_on_cuda/routes.py
lisa_on_cuda/segment_anything/__init__.py
lisa_on_cuda/segment_anything/automatic_mask_generator.py
lisa_on_cuda/segment_anything/build_sam.py
lisa_on_cuda/segment_anything/modeling/__init__.py
lisa_on_cuda/segment_anything/modeling/common.py
lisa_on_cuda/segment_anything/modeling/image_encoder.py
lisa_on_cuda/segment_anything/modeling/mask_decoder.py
lisa_on_cuda-1.4.14.dist-info/LICENSE
lisa_on_cuda-1.4.14.dist-info/METADATA
lisa_on_cuda-1.4.14.dist-info/WHEEL
lisa_on_cuda-1.4.14.dist-info/RECORD
