Metadata-Version: 2.3
Name: lisa-on-cuda
Version: 1.4.14
Summary: LISA (Reasoning Segmentation via Large Language Model) on cuda, now with huggingface ZeroGPU support!
License: Apache 2.0
Author: alessandro trinca tornidor
Author-email: alessandro@trinca.tornidor.com
Requires-Python: >=3.10,<3.12
Classifier: License :: Other/Proprietary License
Classifier: Programming Language :: Python :: 3
Classifier: Programming Language :: Python :: 3.10
Classifier: Programming Language :: Python :: 3.11
Requires-Dist: asgi-correlation-id (>=4.3.4,<5.0.0)
Requires-Dist: bitsandbytes (==0.43.0)
Requires-Dist: einops (>=0.8.0,<0.9.0)
Requires-Dist: fastapi (>=0.115.6,<0.116.0)
Requires-Dist: markdown2 (>=2.5.2,<3.0.0)
Requires-Dist: nh3 (>=0.2.18,<0.3.0)
Requires-Dist: numpy (==1.25.2) ; python_version == "3.10"
Requires-Dist: numpy (>=1.26,<2.0) ; python_version == "3.11"
Requires-Dist: openai (>=1.35.12,<2.0.0)
Requires-Dist: opencv-python-headless (>=4.10.0.84,<5.0.0.0)
Requires-Dist: packaging (>=24.1,<25.0)
Requires-Dist: peft-patched (==0.9.3)
Requires-Dist: pycocotools (>=2.0.8,<3.0.0)
Requires-Dist: requests (>=2.32.3,<3.0.0)
Requires-Dist: samgis-core (==3.0.17)
Requires-Dist: scipy (>=1.14.0,<2.0.0)
Requires-Dist: sentencepiece (>=0.2.0,<0.3.0)
Requires-Dist: shortuuid (>=1.0.13,<2.0.0)
Requires-Dist: spaces (==0.30.2)
Requires-Dist: torch (==2.4.0)
Requires-Dist: torchvision (==0.19.0)
Requires-Dist: tqdm (>=4.66.4,<5.0.0)
Requires-Dist: transformers-backport (==4.31.2)
Requires-Dist: uvicorn (>=0.34.0,<0.35.0)
Project-URL: Demo, https://huggingface.co/spaces/aletrn/lisa-on-cuda/
Project-URL: Source, https://huggingface.co/spaces/aletrn/lisa-on-cuda/
